PythonguruZhongwenXilieJiaochengChuyi/README.md
PythonguruZhongwenXilieJiaochengChuyi/__init__.py
PythonguruZhongwenXilieJiaochengChuyi/__main__.py
PythonguruZhongwenXilieJiaochengChuyi/file.epub
PythonguruZhongwenXilieJiaochengChuyi/index.html
PythonguruZhongwenXilieJiaochengChuyi/css/__init__.py
PythonguruZhongwenXilieJiaochengChuyi/css/annotations.css
PythonguruZhongwenXilieJiaochengChuyi/css/main.css
PythonguruZhongwenXilieJiaochengChuyi/css/normalize.css
PythonguruZhongwenXilieJiaochengChuyi/css/popup.css
PythonguruZhongwenXilieJiaochengChuyi/font/__init__.py
PythonguruZhongwenXilieJiaochengChuyi/font/fontello.eot
PythonguruZhongwenXilieJiaochengChuyi/font/fontello.svg
PythonguruZhongwenXilieJiaochengChuyi/font/fontello.ttf
PythonguruZhongwenXilieJiaochengChuyi/font/fontello.woff
PythonguruZhongwenXilieJiaochengChuyi/img/__init__.py
PythonguruZhongwenXilieJiaochengChuyi/img/annotator-glyph-sprite.png
PythonguruZhongwenXilieJiaochengChuyi/img/annotator-icon-sprite.png
PythonguruZhongwenXilieJiaochengChuyi/img/apple-touch-icon.png
PythonguruZhongwenXilieJiaochengChuyi/img/cancelfullscreen.png
PythonguruZhongwenXilieJiaochengChuyi/img/close.png
PythonguruZhongwenXilieJiaochengChuyi/img/fullscreen.png
PythonguruZhongwenXilieJiaochengChuyi/img/loader.gif
PythonguruZhongwenXilieJiaochengChuyi/img/menu-icon.png
PythonguruZhongwenXilieJiaochengChuyi/img/save.png
PythonguruZhongwenXilieJiaochengChuyi/img/saved.png
PythonguruZhongwenXilieJiaochengChuyi/img/settings-s.png
PythonguruZhongwenXilieJiaochengChuyi/img/settings.png
PythonguruZhongwenXilieJiaochengChuyi/img/star.png
PythonguruZhongwenXilieJiaochengChuyi/js/__init__.py
PythonguruZhongwenXilieJiaochengChuyi/js/epub.js
PythonguruZhongwenXilieJiaochengChuyi/js/epub.min.js
PythonguruZhongwenXilieJiaochengChuyi/js/epub.min.map
PythonguruZhongwenXilieJiaochengChuyi/js/hooks.min.js
PythonguruZhongwenXilieJiaochengChuyi/js/hooks.min.map
PythonguruZhongwenXilieJiaochengChuyi/js/reader.js
pythonguru_zhongwen_xilie_jiaocheng_chuyi-2024.3.5.0.dist-info/METADATA
pythonguru_zhongwen_xilie_jiaocheng_chuyi-2024.3.5.0.dist-info/WHEEL
pythonguru_zhongwen_xilie_jiaocheng_chuyi-2024.3.5.0.dist-info/entry_points.txt
pythonguru_zhongwen_xilie_jiaocheng_chuyi-2024.3.5.0.dist-info/top_level.txt
pythonguru_zhongwen_xilie_jiaocheng_chuyi-2024.3.5.0.dist-info/RECORD
